matplotlib_sankey/__init__.py
matplotlib_sankey/_colors.py
matplotlib_sankey/_patches.py
matplotlib_sankey/_plotting.py
matplotlib_sankey/_types.py
matplotlib_sankey/_utils.py
matplotlib_sankey/_version.py
matplotlib_sankey/py.typed
matplotlib_sankey-0.3.1.dist-info/licenses/LICENSE
matplotlib_sankey-0.3.1.dist-info/WHEEL
matplotlib_sankey-0.3.1.dist-info/METADATA
matplotlib_sankey-0.3.1.dist-info/RECORD
