Metadata-Version: 2.4
Name: matplotlib-sankey
Version: 0.3.1
Summary: Sankey plot for matplotlib
Author: harryhaller001
Maintainer-email: harryhaller001 <harryhaller001@gmail.com>
Requires-Python: >=3.10
Classifier: Development Status :: 3 - Alpha
Classifier: Framework :: Matplotlib
Classifier: Intended Audience :: Science/Research
Classifier: License :: OSI Approved :: MIT License
Classifier: Natural Language :: English
Classifier: Operating System :: OS Independent
Classifier: Programming Language :: Python :: 3 :: Only
Classifier: Programming Language :: Python :: 3.10
Classifier: Programming Language :: Python :: 3.11
Classifier: Programming Language :: Python :: 3.12
Classifier: Programming Language :: Python :: 3.13
Classifier: Typing :: Typed
License-File: LICENSE
Requires-Dist: matplotlib
Requires-Dist: numpy
Requires-Dist: ipykernel ; extra == "docs"
Requires-Dist: ipython ; extra == "docs"
Requires-Dist: ipywidgets ; extra == "docs"
Requires-Dist: myst-parser ; extra == "docs"
Requires-Dist: nbsphinx ; extra == "docs"
Requires-Dist: networkx[default] ; extra == "docs"
Requires-Dist: sphinx>=4 ; extra == "docs"
Requires-Dist: sphinx-autoapi ; extra == "docs"
Requires-Dist: sphinx-autodoc-typehints ; extra == "docs"
Requires-Dist: sphinx-book-theme>=1 ; extra == "docs"
Requires-Dist: coverage ; extra == "test"
Requires-Dist: flit ; extra == "test"
Requires-Dist: mypy ; extra == "test"
Requires-Dist: pre-commit ; extra == "test"
Requires-Dist: pytest ; extra == "test"
Requires-Dist: ruff ; extra == "test"
Requires-Dist: setuptools ; extra == "test"
Requires-Dist: twine>=4.0.2 ; extra == "test"
Project-URL: Documentation, https://harryhaller001.github.io/matplotlib-sankey/
Project-URL: Homepage, https://github.com/harryhaller001/matplotlib-sankey
Project-URL: Source, https://github.com/harryhaller001/matplotlib-sankey
Provides-Extra: docs
Provides-Extra: test
